<?xml version="1.0" encoding="utf-8"?>
<contentList>
	<content contentuid="h7d1c65cbba094da3a34aa9187db9429b8c2g" version="1">Hadoken</content>
	<content contentuid="h96b179a1e59840ccb9cce19ddaa9e52e9dfa" version="1">Canaliser votre énergie intérieur à travers votre poing pour frapper une cible distante [1] fois.</content>
	<content contentuid="h7d1c65cbba094da3a34aa9187db9429b8c2g" version="1">Hadoken</content>
	<content contentuid="h96b179a1e59840ccb9cce19ddaa9e52e9dfa" version="1">Canalisez votre énergie intérieur à travers votre poing pour frapper une cible distante [1] fois.</content>
</contentList>